{"cameraMode":{"drawMode":0,"name":"Shaded","section":"Shading Mode"},"sceneLighting":true,"audioPlay":false,"sceneViewState":{"m_AlwaysRefresh":true,"showFog":true,"showSkybox":true,"showFlares":true,"showImageEffects":true,"showParticleSystems":true,"showVisualEffectGraphs":true,"m_FxEnabled":true},"in2DMode":false,"pivot":{"x":-28.982431411743165,"y":6.250363349914551,"z":-10.553845405578614},"rotation":{"x":0.7071068286895752,"y":0.0,"z":0.0,"w":0.7071068286895752},"size":19.094388961791993,"orthographic":true}